{
    "v2#1.png": {
        "outlier": false,
        "number_of_imprints": 0,
        "details": null,
        "priority": 0
    },
    "v2#5.png": {
        "outlier": false,
        "number_of_imprints": 0,
        "details": null,
        "priority": 0
    },
    "v2#6.png": {
        "outlier": false,
        "number_of_imprints": 0,
        "details": null,
        "priority": 0
    },
    "v2#7.png": {
        "outlier": false,
        "number_of_imprints": 0,
        "details": null,
        "priority": 0
    },
    "v2#8.png": {
        "outlier": false,
        "number_of_imprints": 0,
        "details": null,
        "priority": 0
    },
    "v2#9.png": {
        "outlier": false,
        "number_of_imprints": 0,
        "details": null,
        "priority": 0
    },
    "v2#0__eng@2.png": {
        "outlier": false,
        "number_of_imprints": 2,
        "details": [
            {
                "type": "eng",
                "area": 129,
                "confidence": 0.7859646677970886
            },
            {
                "type": "eng",
                "area": 213,
                "confidence": 0.737157940864563
            }
        ],
        "priority": 2
    },
    "v2#2__eng@1.png": {
        "outlier": false,
        "number_of_imprints": 1,
        "details": [
            {
                "type": "eng",
                "area": 406,
                "confidence": 0.9052624106407166
            }
        ],
        "priority": 1
    },
    "v2#3__eng@1.png": {
        "outlier": false,
        "number_of_imprints": 1,
        "details": [
            {
                "type": "eng",
                "area": 438,
                "confidence": 0.9425839781761169
            }
        ],
        "priority": 1
    },
    "v2#4__eng@1.png": {
        "outlier": false,
        "number_of_imprints": 1,
        "details": [
            {
                "type": "eng",
                "area": 253,
                "confidence": 0.9111096858978271
            }
        ],
        "priority": 1
    }
}